libpyfoscam/__init__.py
libpyfoscam/foscam.py
libpyfoscam-1.2.2.dist-info/LICENSE
libpyfoscam-1.2.2.dist-info/METADATA
libpyfoscam-1.2.2.dist-info/WHEEL
libpyfoscam-1.2.2.dist-info/top_level.txt
libpyfoscam-1.2.2.dist-info/RECORD
