Metadata-Version: 2.1
Name: libpyfoscam
Version: 1.2.2
Summary: Python Library for Foscam IP Cameras
Home-page: https://github.com/krmarien/python-foscam
Author: Viswanathan S
Author-email: viswa.swami@gmail.com
License: LGPLv3+
Keywords: foscam,Camera,IPC
License-File: LICENSE
